django_model_ya_publisher-0.4.0.dev1.dist-info/DESCRIPTION.rst
django_model_ya_publisher-0.4.0.dev1.dist-info/METADATA
django_model_ya_publisher-0.4.0.dev1.dist-info/RECORD
django_model_ya_publisher-0.4.0.dev1.dist-info/WHEEL
django_model_ya_publisher-0.4.0.dev1.dist-info/metadata.json
django_model_ya_publisher-0.4.0.dev1.dist-info/top_level.txt
publisher/__init__.py
publisher/admin.py
publisher/managers.py
publisher/middleware.py
publisher/models.py
publisher/signals.py
publisher/utils.py
publisher/version.py
publisher/views.py
publisher/management/__init__.py
publisher/management/commands/__init__.py
publisher/management/commands/publish_model.py
publisher/management/commands/update_permissions.py
publisher/static/publisher/publisher.css
publisher/static/publisher/publisher.js
publisher/static/publisher/images/icons.png
publisher/templates/publisher/change_form.html
publisher/templates/publisher/change_list_publish.html
publisher/templates/publisher/change_list_publish_status.html
publisher/templates/publisher/hvad/change_form.html
publisher/templates/publisher/parler/change_form.html
