Metadata-Version: 2.0
Name: django-model-ya-publisher
Version: 0.4.0.dev1
Summary: Handy mixin/abstract class for providing a "publisher workflow" to arbitrary Django models.
Home-page: https://github.com/wearehoods/django-ya-model-publisher
Author: Jens Diemer
Author-email: model-ya-publisher@jensdiemer.de
License: BSD
Keywords: publisher django cms parler workflow model-publisher
Platform: UNKNOWN
Classifier: Development Status :: 3 - Alpha
Classifier: Environment :: Web Environment
Classifier: Framework :: Django
Classifier: Intended Audience :: Developers
Classifier: License :: OSI Approved :: BSD License
Classifier: Operating System :: OS Independent
Classifier: Programming Language :: Python
Classifier: Programming Language :: Python :: 2
Classifier: Programming Language :: Python :: 2.6
Classifier: Programming Language :: Python :: 2.7
Classifier: Programming Language :: Python :: 3
Classifier: Programming Language :: Python :: 3.4
Classifier: Topic :: Internet :: WWW/HTTP :: Dynamic Content :: Content Management System
Classifier: Topic :: Software Development :: Libraries :: Python Modules
